CHANGES.txt
MANIFEST.in
README.md
README.txt
setup.py
layerstack/__init__.py
layerstack/_version.py
layerstack/args.py
layerstack/layer.py
layerstack/layer.template
layerstack/stack.py
layerstack.egg-info/PKG-INFO
layerstack.egg-info/SOURCES.txt
layerstack.egg-info/dependency_links.txt
layerstack.egg-info/entry_points.txt
layerstack.egg-info/requires.txt
layerstack.egg-info/top_level.txt
layerstack/tests/__init__.py
layerstack/tests/conftest.py
layerstack/tests/test_args_kwargs.py
layerstack/tests/test_layer.py
layerstack/tests/test_layerbase.py
layerstack/tests/test_session.py
layerstack/tests/test_stack.py
layerstack/tests/test_stack_save_load.py
layerstack/tests/layer_library/test_kwarg_name_clashes/layer.py
layerstack/tests/layer_library/test_kwargs_with_dashes/layer.py
layerstack/tests/layer_library/test_list_args/layer.py
layerstack/tests/layer_library/test_model_dependent_args_kwargs/layer.py
layerstack/tests/layer_library/test_model_layer_base/layer.py
layerstack/tests/layer_library/test_model_layer_base2/layer.py