Metadata-Version: 2.1
Name: layerstack
Version: 0.4.0
Summary: Python package for assembling, sharing, and running workflows, especially those associated with modifying, running, and analyzing simulation models
Home-page: https://github.com/Smart-DS/layerstack
Author: Elaine Hale, Michael Rossol
Author-email: elaine.hale@nrel.gov
License: UNKNOWN
Platform: UNKNOWN
Classifier: Intended Audience :: Science/Research
Classifier: Natural Language :: English
Classifier: Programming Language :: Python
Classifier: Programming Language :: Python :: 3.6
Classifier: Programming Language :: Python :: 3.7
Requires-Python: >=3.6
Provides-Extra: dev
